envresolve/__init__.py
envresolve/api.py
envresolve/exceptions.py
envresolve/models.py
envresolve/py.typed
envresolve/application/__init__.py
envresolve/application/expanders.py
envresolve/application/resolver.py
envresolve/providers/__init__.py
envresolve/providers/azure_kv.py
envresolve/providers/base.py
envresolve/services/__init__.py
envresolve/services/expansion.py
envresolve/services/reference.py
envresolve-0.1.11.dist-info/licenses/LICENSE
envresolve-0.1.11.dist-info/METADATA
envresolve-0.1.11.dist-info/WHEEL
envresolve-0.1.11.dist-info/top_level.txt
envresolve-0.1.11.dist-info/RECORD
