Metadata-Version: 2.4
Name: envresolve
Version: 0.1.11
Summary: Resolve env vars from secret stores.
Author: osoken
License-Expression: MIT
Project-URL: Homepage, https://github.com/osoekawaitlab/envresolve
Project-URL: Documentation, https://osoekawaitlab.github.io/envresolve/
Project-URL: Repository, https://github.com/osoekawaitlab/envresolve
Classifier: Development Status :: 4 - Beta
Classifier: Intended Audience :: Developers
Classifier: Operating System :: OS Independent
Classifier: Programming Language :: Python :: 3 :: Only
Classifier: Programming Language :: Python :: 3.10
Classifier: Programming Language :: Python :: 3.11
Classifier: Programming Language :: Python :: 3.12
Classifier: Programming Language :: Python :: 3.13
Classifier: Programming Language :: Python :: 3.14
Classifier: Typing :: Typed
Requires-Python: >=3.10
License-File: LICENSE
Requires-Dist: python-dotenv>=1.1.1
Provides-Extra: azure
Requires-Dist: azure-identity>=1.19.0; extra == "azure"
Requires-Dist: azure-keyvault-secrets>=4.9.0; extra == "azure"
Dynamic: license-file
